_sphinx/_source/conf.py
acspype/__init__.py
acspype/_checks.py
acspype/core.py
acspype/dev.py
acspype/experimental.py
acspype/packet.py
acspype/processing.py
acspype/qaqc.py
acspype/stream.py
acspype/structures.py
acspype/ts4cor.py
acspype/ts4cor_sigma.py
acspype/tscor.py
acspype/uncertainty.py
acspype/utils/__init__.py
acspype/utils/core.py
acspype/utils/ooi.py
acspype-0.3.6.dist-info/licenses/LICENSE
tests/test_acsdev.py
tests/test_singleton.py
tests/test_ts4cor_reader.py
tests/test_xarray.py
acspype-0.3.6.dist-info/METADATA
acspype-0.3.6.dist-info/WHEEL
acspype-0.3.6.dist-info/top_level.txt
acspype-0.3.6.dist-info/RECORD
