Metadata-Version: 2.4
Name: acspype
Version: 0.3.6
Summary: A Python package for serial data acquisition and advanced processing for the Sea-Bird Scientific ACS.
Author-email: Ian Black <iantimothyblack@gmail.com>, Thor Black <j.thor.black@gmail.com>
License-Expression: MIT
Project-URL: Repository, https://github.com/IanTBlack/acspype
Project-URL: Issues, https://github.com/IanTBlack/acspype/issues
Project-URL: Discussions, https://github.com/IanTBlack/acspype/discussions
Project-URL: Additional Information, https://github.com/IanTBlack/acspype/tree/main/info
Project-URL: Documentation, https://iantblack.github.io/acspype/
Keywords: AC-S,Sea-Bird Scientific,SBS,WETLabs,oceanography,absorption,attenuation
Classifier: Development Status :: 4 - Beta
Classifier: Intended Audience :: Science/Research
Classifier: Topic :: Scientific/Engineering
Classifier: Programming Language :: Python :: 3.10
Classifier: Programming Language :: Python :: 3.11
Classifier: Programming Language :: Python :: 3.12
Classifier: Programming Language :: Python :: 3.13
Requires-Python: >=3.10
License-File: LICENSE
Requires-Dist: bottleneck
Requires-Dist: netCDF4
Requires-Dist: numpy
Requires-Dist: pandas
Requires-Dist: pyserial
Requires-Dist: requests
Requires-Dist: scipy
Requires-Dist: uncertainties
Requires-Dist: xarray
Provides-Extra: dev-tools
Requires-Dist: fsspec; extra == "dev-tools"
Requires-Dist: gsw; extra == "dev-tools"
Requires-Dist: jupyter; extra == "dev-tools"
Requires-Dist: ipykernel; extra == "dev-tools"
Requires-Dist: ipympl; extra == "dev-tools"
Requires-Dist: matplotlib; extra == "dev-tools"
Requires-Dist: pytest; extra == "dev-tools"
Requires-Dist: uv; extra == "dev-tools"
Requires-Dist: sphinx; extra == "dev-tools"
Requires-Dist: sphinx_rtd_theme; extra == "dev-tools"
Requires-Dist: m2r2; extra == "dev-tools"
Requires-Dist: myst-nb; extra == "dev-tools"
Dynamic: license-file
